setup.py
url2feed/__init__.py
url2feed/fetcher.py
url2feed/helpers.py
url2feed/url2feed.py
url2feed.egg-info/PKG-INFO
url2feed.egg-info/SOURCES.txt
url2feed.egg-info/dependency_links.txt
url2feed.egg-info/entry_points.txt
url2feed.egg-info/requires.txt
url2feed.egg-info/top_level.txt