Metadata-Version: 1.1
Name: url2feed
Version: 0.0.1
Summary: Extract feed from url.
Home-page: https://github.com/gosusnp/url2feed
Author: snp
Author-email: gosu.snp@gmail.com
License: MIT/X
Keywords: url2feed,url,rss,atom,feed
Platform: UNKNOWN
Classifier: Environment :: Console
Classifier: Development Status :: 3 - Alpha
Classifier: Programming Language :: Python
Classifier: Topic :: Internet
